mqttwarn/__init__.py
mqttwarn/__main__.py
mqttwarn/commands.py
mqttwarn/configuration.py
mqttwarn/context.py
mqttwarn/core.py
mqttwarn/cron.py
mqttwarn/model.py
mqttwarn/util.py
mqttwarn/examples/__init__.py
mqttwarn/examples/basic/mqttwarn.ini
mqttwarn/examples/basic/udf.py
mqttwarn/services/__init__.py
mqttwarn/services/alexa-notify-me.py
mqttwarn/services/amqp.py
mqttwarn/services/apns.py
mqttwarn/services/apprise.py
mqttwarn/services/apprise_multi.py
mqttwarn/services/apprise_single.py
mqttwarn/services/apprise_util.py
mqttwarn/services/asterisk.py
mqttwarn/services/autoremote.py
mqttwarn/services/azure_iot.py
mqttwarn/services/carbon.py
mqttwarn/services/celery.py
mqttwarn/services/chromecast.py
mqttwarn/services/dbus.py
mqttwarn/services/desktopnotify.py
mqttwarn/services/dnsupdate.py
mqttwarn/services/emoncms.py
mqttwarn/services/execute.py
mqttwarn/services/fbchat.py
mqttwarn/services/file.py
mqttwarn/services/freeswitch.py
mqttwarn/services/gss2.py
mqttwarn/services/hangbot.py
mqttwarn/services/http_urllib.py
mqttwarn/services/icinga2.py
mqttwarn/services/ifttt.py
mqttwarn/services/influxdb.py
mqttwarn/services/ionic.py
mqttwarn/services/irccat.py
mqttwarn/services/linuxnotify.py
mqttwarn/services/log.py
mqttwarn/services/mattermost.py
mqttwarn/services/mqtt.py
mqttwarn/services/mqtt_filter.py
mqttwarn/services/mqttpub.py
mqttwarn/services/mysql.py
mqttwarn/services/mysql_dynamic.py
mqttwarn/services/mysql_remap.py
mqttwarn/services/mythtv.py
mqttwarn/services/nntp.py
mqttwarn/services/noop.py
mqttwarn/services/nsca.py
mqttwarn/services/ntfy.py
mqttwarn/services/osxsay.py
mqttwarn/services/pastebinpub.py
mqttwarn/services/pipe.py
mqttwarn/services/postgres.py
mqttwarn/services/prowl.py
mqttwarn/services/pushbullet.py
mqttwarn/services/pushover.py
mqttwarn/services/pushsafer.py
mqttwarn/services/redispub.py
mqttwarn/services/rrdtool.py
mqttwarn/services/serial.py
mqttwarn/services/slack.py
mqttwarn/services/slixmpp.py
mqttwarn/services/smtp.py
mqttwarn-0.35.0.dist-info/LICENSE
mqttwarn-0.35.0.dist-info/METADATA
mqttwarn-0.35.0.dist-info/WHEEL
mqttwarn-0.35.0.dist-info/entry_points.txt
mqttwarn-0.35.0.dist-info/top_level.txt
mqttwarn-0.35.0.dist-info/RECORD
