Metadata-Version: 2.1
Name: mqttwarn
Version: 0.35.0
Summary: mqttwarn - subscribe to MQTT topics and notify pluggable services
Home-page: https://github.com/mqtt-tools/mqttwarn
Author: Jan-Piet Mens, Ben Jones, Andreas Motl
Author-email: jpmens@gmail.com
License: EPL 2.0
Keywords: mqtt notification plugins data acquisition push transformation engine mosquitto
Classifier: Development Status :: 5 - Production/Stable
Classifier: Environment :: Console
Classifier: Environment :: Plugins
Classifier: Intended Audience :: Developers
Classifier: Intended Audience :: Education
Classifier: Intended Audience :: Information Technology
Classifier: Intended Audience :: Manufacturing
Classifier: Intended Audience :: Science/Research
Classifier: Intended Audience :: System Administrators
Classifier: Intended Audience :: Telecommunications Industry
Classifier: License :: OSI Approved :: Eclipse Public License 2.0 (EPL-2.0)
Classifier: Operating System :: POSIX
Classifier: Operating System :: Unix
Classifier: Operating System :: MacOS
Classifier: Programming Language :: Python
Classifier: Programming Language :: Python :: 3.6
Classifier: Programming Language :: Python :: 3.7
Classifier: Programming Language :: Python :: 3.8
Classifier: Programming Language :: Python :: 3.9
Classifier: Programming Language :: Python :: 3.10
Classifier: Programming Language :: Python :: 3.11
Classifier: Programming Language :: Python :: 3.12
Classifier: Topic :: Communications
Classifier: Topic :: Education
Classifier: Topic :: Internet
Classifier: Topic :: Internet :: WWW/HTTP
Classifier: Topic :: Internet :: XMPP
Classifier: Topic :: Scientific/Engineering :: Interface Engine/Protocol Translator
Classifier: Topic :: Software Development :: Embedded Systems
Classifier: Topic :: Software Development :: Libraries
Classifier: Topic :: Software Development :: Pre-processors
Classifier: Topic :: Software Development :: Testing
Classifier: Topic :: System :: Archiving
Classifier: Topic :: System :: Distributed Computing
Classifier: Topic :: System :: Monitoring
Classifier: Topic :: System :: Networking :: Monitoring
Classifier: Topic :: System :: Systems Administration
Classifier: Topic :: Text Processing
Classifier: Topic :: Utilities
License-File: LICENSE
Requires-Dist: attrs <23
Requires-Dist: docopt <1
Requires-Dist: funcy <3
Requires-Dist: future <1,>=0.18.0
Requires-Dist: jinja2 <4
Requires-Dist: paho-mqtt <2
Requires-Dist: requests <3
Requires-Dist: six <2
Requires-Dist: importlib-metadata ; python_version < "3.8"
Requires-Dist: importlib-resources ; python_version < "3.8"
Provides-Extra: all
Requires-Dist: apns >=2.0.1 ; extra == 'all'
Requires-Dist: apprise <2,>=1.3 ; extra == 'all'
Requires-Dist: pyst2 >=0.5.0 ; extra == 'all'
Requires-Dist: celery ; extra == 'all'
Requires-Dist: dnspython >=1.15.0 ; extra == 'all'
Requires-Dist: fbchat >=1.3.6 ; extra == 'all'
Requires-Dist: gspread >=2.1.1 ; extra == 'all'
Requires-Dist: oauth2client >=4.1.2 ; extra == 'all'
Requires-Dist: pynsca >=1.6 ; extra == 'all'
Requires-Dist: desktop-notifier <4 ; extra == 'all'
Requires-Dist: Pastebin >=1.1.2 ; extra == 'all'
Requires-Dist: psycopg2-binary >=2.7.4 ; extra == 'all'
Requires-Dist: pyprowl >=3.0.1 ; extra == 'all'
Requires-Dist: redis >=2.10.6 ; extra == 'all'
Requires-Dist: pyserial >=3.4 ; extra == 'all'
Requires-Dist: slack-sdk >=3.1.0 ; extra == 'all'
Requires-Dist: Mastodon.py >=1.2.2 ; extra == 'all'
Requires-Dist: twilio >=6.11.0 ; extra == 'all'
Requires-Dist: python-twitter >=3.4.1 ; extra == 'all'
Requires-Dist: websocket-client >=0.47.0 ; extra == 'all'
Requires-Dist: xmpppy >=0.6.1 ; extra == 'all'
Requires-Dist: dnspython >=1.16.0 ; extra == 'all'
Requires-Dist: slixmpp >=1.5.2 ; extra == 'all'
Requires-Dist: mqttwarn-contrib ; extra == 'all'
Requires-Dist: puka >=0.0.7 ; (python_version < "3.12") and extra == 'all'
Requires-Dist: pychromecast >=7.5.0 ; (python_version >= "3.7") and extra == 'all'
Requires-Dist: google-api-python-client <2 ; (python_version >= "3.7") and extra == 'all'
Requires-Dist: paramiko >=2.4.1 ; (python_version >= "3.7") and extra == 'all'
Provides-Extra: amqp
Requires-Dist: puka >=0.0.7 ; (python_version < "3.12") and extra == 'amqp'
Provides-Extra: apns
Requires-Dist: apns >=2.0.1 ; extra == 'apns'
Provides-Extra: apprise
Requires-Dist: apprise <2,>=1.3 ; extra == 'apprise'
Provides-Extra: asterisk
Requires-Dist: pyst2 >=0.5.0 ; extra == 'asterisk'
Provides-Extra: celery
Requires-Dist: celery ; extra == 'celery'
Provides-Extra: chromecast
Requires-Dist: pychromecast >=7.5.0 ; (python_version >= "3.7") and extra == 'chromecast'
Provides-Extra: contrib
Requires-Dist: mqttwarn-contrib ; extra == 'contrib'
Provides-Extra: desktopnotify
Requires-Dist: desktop-notifier <4 ; extra == 'desktopnotify'
Provides-Extra: develop
Requires-Dist: black <23 ; extra == 'develop'
Requires-Dist: build <1 ; extra == 'develop'
Requires-Dist: mypy <1.3 ; extra == 'develop'
Requires-Dist: poethepoet <1 ; extra == 'develop'
Requires-Dist: sphinx-autobuild ; extra == 'develop'
Requires-Dist: ruff ==0.0.254 ; (python_version >= "3.7") and extra == 'develop'
Provides-Extra: dnsupdate
Requires-Dist: dnspython >=1.15.0 ; extra == 'dnsupdate'
Provides-Extra: fbchat
Requires-Dist: fbchat >=1.3.6 ; extra == 'fbchat'
Provides-Extra: gss2
Requires-Dist: gspread >=2.1.1 ; extra == 'gss2'
Requires-Dist: oauth2client >=4.1.2 ; extra == 'gss2'
Requires-Dist: google-api-python-client <2 ; (python_version >= "3.7") and extra == 'gss2'
Provides-Extra: mysql
Requires-Dist: mysql ; extra == 'mysql'
Provides-Extra: mysql_dynamic
Requires-Dist: mysqlclient ; extra == 'mysql_dynamic'
Provides-Extra: nsca
Requires-Dist: pynsca >=1.6 ; extra == 'nsca'
Provides-Extra: pastebinpub
Requires-Dist: Pastebin >=1.1.2 ; extra == 'pastebinpub'
Provides-Extra: postgres
Requires-Dist: psycopg2-binary >=2.7.4 ; extra == 'postgres'
Provides-Extra: prowl
Requires-Dist: pyprowl >=3.0.1 ; extra == 'prowl'
Provides-Extra: pushbullet
Provides-Extra: redispub
Requires-Dist: redis >=2.10.6 ; extra == 'redispub'
Provides-Extra: rrdtool
Requires-Dist: rrdtool >=0.1.12 ; extra == 'rrdtool'
Provides-Extra: serial
Requires-Dist: pyserial >=3.4 ; extra == 'serial'
Provides-Extra: slack
Requires-Dist: slack-sdk >=3.1.0 ; extra == 'slack'
Provides-Extra: slixmpp
Requires-Dist: slixmpp >=1.5.2 ; extra == 'slixmpp'
Provides-Extra: ssh
Requires-Dist: paramiko >=2.4.1 ; (python_version >= "3.7") and extra == 'ssh'
Provides-Extra: test
Requires-Dist: pytest <8 ; extra == 'test'
Requires-Dist: pytest-cov <5 ; extra == 'test'
Requires-Dist: pytest-mock <4 ; extra == 'test'
Requires-Dist: pytest-mqtt <1 ; extra == 'test'
Requires-Dist: tox <4 ; extra == 'test'
Requires-Dist: requests-toolbelt <2,>=1 ; extra == 'test'
Requires-Dist: responses <1,>=0.13.3 ; extra == 'test'
Requires-Dist: pyfakefs <6,>=4.5 ; extra == 'test'
Requires-Dist: apns >=2.0.1 ; extra == 'test'
Requires-Dist: apprise <2,>=1.3 ; extra == 'test'
Requires-Dist: pyst2 >=0.5.0 ; extra == 'test'
Requires-Dist: celery ; extra == 'test'
Requires-Dist: dnspython >=1.15.0 ; extra == 'test'
Requires-Dist: fbchat >=1.3.6 ; extra == 'test'
Requires-Dist: gspread >=2.1.1 ; extra == 'test'
Requires-Dist: oauth2client >=4.1.2 ; extra == 'test'
Requires-Dist: pynsca >=1.6 ; extra == 'test'
Requires-Dist: desktop-notifier <4 ; extra == 'test'
Requires-Dist: Pastebin >=1.1.2 ; extra == 'test'
Requires-Dist: psycopg2-binary >=2.7.4 ; extra == 'test'
Requires-Dist: pyprowl >=3.0.1 ; extra == 'test'
Requires-Dist: redis >=2.10.6 ; extra == 'test'
Requires-Dist: pyserial >=3.4 ; extra == 'test'
Requires-Dist: slack-sdk >=3.1.0 ; extra == 'test'
Requires-Dist: Mastodon.py >=1.2.2 ; extra == 'test'
Requires-Dist: twilio >=6.11.0 ; extra == 'test'
Requires-Dist: python-twitter >=3.4.1 ; extra == 'test'
Requires-Dist: websocket-client >=0.47.0 ; extra == 'test'
Requires-Dist: xmpppy >=0.6.1 ; extra == 'test'
Requires-Dist: dnspython >=1.16.0 ; extra == 'test'
Requires-Dist: slixmpp >=1.5.2 ; extra == 'test'
Requires-Dist: mqttwarn-contrib ; extra == 'test'
Requires-Dist: puka >=0.0.7 ; (python_version < "3.12") and extra == 'test'
Requires-Dist: dataclasses ; (python_version < "3.7") and extra == 'test'
Requires-Dist: pychromecast >=7.5.0 ; (python_version >= "3.7") and extra == 'test'
Requires-Dist: google-api-python-client <2 ; (python_version >= "3.7") and extra == 'test'
Requires-Dist: paramiko >=2.4.1 ; (python_version >= "3.7") and extra == 'test'
Provides-Extra: tootpaste
Requires-Dist: Mastodon.py >=1.2.2 ; extra == 'tootpaste'
Provides-Extra: twilio
Requires-Dist: twilio >=6.11.0 ; extra == 'twilio'
Provides-Extra: twitter
Requires-Dist: python-twitter >=3.4.1 ; extra == 'twitter'
Provides-Extra: websocket
Requires-Dist: websocket-client >=0.47.0 ; extra == 'websocket'
Provides-Extra: xmpp
Requires-Dist: xmpppy >=0.6.1 ; extra == 'xmpp'
Requires-Dist: dnspython >=1.16.0 ; extra == 'xmpp'
